ACT7multiplexer/2x1/ACT7_2by1_GL.v
module ACT7_2by1_GL(Y, D1, D0, S);
input D1, D0, S;
output Y;
wire W1NOT, W2AND, W3AND;

not n1(W1NOT, S);
and a1(W2AND, D1, S); 
and a2(W3AND, W1NOT, D0);
or o1(Y, W2AND, W3AND);
endmodule

ACT7multiplexer/2x1/ACT7_2by1_GL_tb.v
`include "ACT7_2by1_GL.v"
module ACT7_2by1_GL_tb;
	reg D1, D0, S;
	wire Y;
	ACT7_2by1_GL Instance0(Y, D1, D0, S);
initial begin
	S = 0; D0 = 0; D1 = 0;
 #1	S = 0; D0 = 0; D1 = 1;
 #1	S = 0; D0 = 1; D1 = 0;
 #1	S = 0; D0 = 1; D1 = 1;
 #1	S = 1; D0 = 0; D1 = 0;
 #1	S = 1; D0 = 0; D1 = 1;
 #1	S = 1; D0 = 1; D1 = 0;
 #1	S = 1; D0 = 1; D1 = 1;
 #1;
end

initial begin
	$monitor("%t | D1 = %d | D0 = %d | S = %d | Y = %d", $time, D1, D0, S, Y);
	$dumpfile("ACT7_2by1_GL.vcd");
	$dumpvars();
end
endmodule

ACT7multiplexer/2x1/ACT7_2by1_GL.vcd
$date
	Sun Nov 23 10:24:38 2025
$end
$version
	Icarus Verilog
$end
$timescale
	1s
$end
$scope module ACT7_2by1_GL_tb $end
$var wire 1 ! Y $end
$var reg 1 " D0 $end
$var reg 1 # D1 $end
$var reg 1 $ S $end
$scope module Instance0 $end
$var wire 1 " D0 $end
$var wire 1 # D1 $end
$var wire 1 $ S $end
$var wire 1 % W1NOT $end
$var wire 1 & W2AND $end
$var wire 1 ' W3AND $end
$var wire 1 ! Y $end
$upscope $end
$upscope $end
$enddefinitions $end
$comment Show the parameter values. $end
$dumpall
$end
#0
$dumpvars
0'
0&
1%
0$
0#
0"
0!
$end
#1
1#
#2
1!
1'
0#
1"
#3
1#
#4
0!
0'
0%
0#
0"
1$
#5
1!
1&
1#
#6
0!
0&
0#
1"
#7
1!
1&
1#
