HDLQuiz#1/OR_data_flow.v
module OR_data_flow (output Y, input A, B, C);
	assign Y = A || B || C;
endmodule

HDLQuiz#1/OR_data_flow_tb.v
`include "OR_data_flow.v"
module OR_data_flow_tb;
	reg A, B, C;
	wire Y;
	OR_data_flow instance0 (Y, A, B, C);
initial begin
	A = 0; B = 0; C = 0;
 #1	A = 0; B = 0; C = 1;
 #1	A = 0; B = 1; C = 0;
 #1	A = 0; B = 1; C = 1;
 #1	A = 1; B = 0; C = 0;
 #1	A = 1; B = 0; C = 1;
 #1	A = 1; B = 1; C = 0;
 #1	A = 1; B = 1; C = 1;
 #1;
end

initial begin
	$monitor("%t | A = %d | B = %d | C = %d | Y = %d", $time, A, B, C, Y);
	$dumpfile("OR_data_flow.vcd");
	$dumpvars();
end
endmodule

HDLQuiz#1/OR_data_flow.vcd
$date
	Fri Oct 03 09:14:22 2025
$end
$version
	Icarus Verilog
$end
$timescale
	1s
$end
$scope module OR_data_flow_tb $end
$var wire 1 ! Y $end
$var reg 1 " A $end
$var reg 1 # B $end
$var reg 1 $ C $end
$scope module instance0 $end
$var wire 1 " A $end
$var wire 1 # B $end
$var wire 1 $ C $end
$var wire 1 ! Y $end
$upscope $end
$upscope $end
$enddefinitions $end
$comment Show the parameter values. $end
$dumpall
$end
#0
$dumpvars
0$
0#
0"
0!
$end
#1
1!
1$
#2
0$
1#
#3
1$
#4
0$
0#
1"
#5
1$
#6
0$
1#
#7
1$
