ACT5/ACT_5_B.v
module ACT_5_B (S, Cout, A, B, C);
input A, B, C;
output reg S, Cout;
always @(*) begin	
S = (A^B)^C;
Cout = ((A^B)&C) | (A&B);
end
endmodule

ACT5/ACT_5_B_tb.v
`include "ACT_5_B.v"
module ACT_5_B_tb;
	reg A, B, C;
	wire S, Cout;
	ACT_5_B Instance0(S, Cout, A, B, C);

initial begin
	A = 0; B = 0; C = 0;
 #1	A = 1; B = 0; C = 0;
 #1	A = 0; B = 1; C = 0;
 #1	A = 1; B = 1; C = 0;
 #1	A = 0; B = 0; C = 1;
 #1	A = 1; B = 0; C = 1;
 #1	A = 0; B = 1; C = 1;
 #1	A = 1; B = 1; C = 1;
 #1;
end

initial begin
	$monitor("%t | A = %d | B = %d | C = %d | Cout = %d | S = %d", $time, A, B, C, Cout, S);
	$dumpfile("ACT_5_GL.vcd");
	$dumpvars();
end
endmodule

ACT5/ACT_5_GL.vcd
$date
	Tue Oct 28 09:31:46 2025
$end
$version
	Icarus Verilog
$end
$timescale
	1s
$end
$scope module ACT_5_B_tb $end
$var wire 1 ! S $end
$var wire 1 " Cout $end
$var reg 1 # A $end
$var reg 1 $ B $end
$var reg 1 % C $end
$scope module Instance0 $end
$var wire 1 # A $end
$var wire 1 $ B $end
$var wire 1 % C $end
$var reg 1 " Cout $end
$var reg 1 ! S $end
$upscope $end
$upscope $end
$enddefinitions $end
$comment Show the parameter values. $end
$dumpall
$end
#0
$dumpvars
0%
0$
0#
0"
0!
$end
#1
1!
1#
#2
1$
0#
#3
1"
0!
1#
#4
0"
1!
1%
0$
0#
#5
1"
0!
1#
#6
1$
0#
#7
1!
1#
