ACT7multiplexer/8x1/ACT7_8by1_GL.v
module ACT7_8by1_GL(output Y, input D7,D6,D5,D4,D3,D2,D1,D0,S0,S1,S2);
wire s2not, s1not, s0not, andD0, andD1, andD2, andD3, andD4, andD5, andD6,andD7 ;
not (s1not,S1);
not(s0not,S0);
not(s2not,S2);

and(andD7,S0,S1,S2,D3);
and(andD6,s0not,S1,S2,D2);
and(andD5,s1not,s2not, S2,D1);
and(andD4,s0not,s1not,S2,D0);
and(andD3,S0,S1,s2not,D3);
and(andD2,s0not,S1,s2not,D2);
and(andD1,s1not,s2not, S0,D1);
and(andD0,s0not,s1not,s2not,D0);

or(Y,andD7,andD6, andD5,andD4,andD3,andD2,andD1,andD0);


endmodule

ACT7multiplexer/8x1/ACT7_8by1_GL_tb.v
`include "ACT7_8by1_GL.v"

module ACT7_8by1_GL_tb;
reg D7,D6,D5,D4,D3,D2,D1,D0,S0,S1,S2;
wire Y;


integer i;
reg [10:0] vec;   // 11 input bits

  ACT7_8by1_GL pins(Y, D7, D6, D5, D4, D3, D2, D1, D0, S0, S1, S2);

  
  initial begin
    for(i = 0; i < 2048; i = i + 1) begin
      vec = i;

      // D7 first → S2 last
      {S2, S1, S0, D0, D1, D2, D3, D4, D5, D6, D7} = vec;

      #1;
    end
    #1 $finish;
  end

initial begin  // D7, D6, D5, D4, D3,D2,D1,D0
$monitor("%t | S2=%d | S1=%d | S0=%d | D0=%d | D1=%d | D2=%d | D3=%d | D4=%d | D5=%d | D6=%d | D7=%d | Y=%d",$time, S2, S1,S0,D0,D1,D2,D3,D4,D5,D6,D7,Y);
$dumpfile("gate.vcd");
$dumpvars();

end
endmodule

ACT7multiplexer/8x1/gate.vcd
$date
	Sun Nov 23 14:54:31 2025
$end
$version
	Icarus Verilog
$end
$timescale
	1s
$end
$scope module ACT7_8by1_GL_tb $end
$var wire 1 ! Y $end
$var reg 1 " D0 $end
$var reg 1 # D1 $end
$var reg 1 $ D2 $end
$var reg 1 % D3 $end
$var reg 1 & D4 $end
$var reg 1 ' D5 $end
$var reg 1 ( D6 $end
$var reg 1 ) D7 $end
$var reg 1 * S0 $end
$var reg 1 + S1 $end
$var reg 1 , S2 $end
$var reg 11 - vec [10:0] $end
$var integer 32 . i [31:0] $end
$scope module pins $end
$var wire 1 " D0 $end
$var wire 1 # D1 $end
$var wire 1 $ D2 $end
$var wire 1 % D3 $end
$var wire 1 & D4 $end
$var wire 1 ' D5 $end
$var wire 1 ( D6 $end
$var wire 1 ) D7 $end
$var wire 1 * S0 $end
$var wire 1 + S1 $end
$var wire 1 , S2 $end
$var wire 1 ! Y $end
$var wire 1 / andD0 $end
$var wire 1 0 andD1 $end
$var wire 1 1 andD2 $end
$var wire 1 2 andD3 $end
$var wire 1 3 andD4 $end
$var wire 1 4 andD5 $end
$var wire 1 5 andD6 $end
$var wire 1 6 andD7 $end
$var wire 1 7 s0not $end
$var wire 1 8 s1not $end
$var wire 1 9 s2not $end
$upscope $end
$upscope $end
$enddefinitions $end
$comment Show the parameter values. $end
$dumpall
$end
#0
$dumpvars
19
18
17
06
05
04
03
02
01
00
0/
b0 .
b0 -
0,
0+
0*
0)
0(
0'
0&
0%
0$
0#
0"
0!
$end
#1
1)
b1 -
b1 .
#2
1(
0)
b10 -
b10 .
#3
1)
b11 -
b11 .
#4
1'
0(
0)
b100 -
b100 .
#5
1)
b101 -
b101 .
#6
1(
0)
b110 -
b110 .
#7
1)
b111 -
b111 .
#8
1&
0'
0(
0)
b1000 -
b1000 .
#9
1)
b1001 -
b1001 .
#10
1(
0)
b1010 -
b1010 .
#11
1)
b1011 -
b1011 .
#12
1'
0(
0)
b1100 -
b1100 .
#13
1)
b1101 -
b1101 .
#14
1(
0)
b1110 -
b1110 .
#15
1)
b1111 -
b1111 .
#16
1%
0&
0'
0(
0)
b10000 -
b10000 .
#17
1)
b10001 -
b10001 .
#18
1(
0)
b10010 -
b10010 .
#19
1)
b10011 -
b10011 .
#20
1'
0(
0)
b10100 -
b10100 .
#21
1)
b10101 -
b10101 .
#22
1(
0)
b10110 -
b10110 .
#23
1)
b10111 -
b10111 .
#24
1&
0'
0(
0)
b11000 -
b11000 .
#25
1)
b11001 -
b11001 .
#26
1(
0)
b11010 -
b11010 .
#27
1)
b11011 -
b11011 .
#28
1'
0(
0)
b11100 -
b11100 .
#29
1)
b11101 -
b11101 .
#30
1(
0)
b11110 -
b11110 .
#31
1)
b11111 -
b11111 .
#32
1$
0%
0&
0'
0(
0)
b100000 -
b100000 .
#33
1)
b100001 -
b100001 .
#34
1(
0)
b100010 -
b100010 .
#35
1)
b100011 -
b100011 .
#36
1'
0(
0)
b100100 -
b100100 .
#37
1)
b100101 -
b100101 .
#38
1(
0)
b100110 -
b100110 .
#39
1)
b100111 -
b100111 .
#40
1&
0'
0(
0)
b101000 -
b101000 .
#41
1)
b101001 -
b101001 .
#42
1(
0)
b101010 -
b101010 .
#43
1)
b101011 -
b101011 .
#44
1'
0(
0)
b101100 -
b101100 .
#45
1)
b101101 -
b101101 .
#46
1(
0)
b101110 -
b101110 .
#47
1)
b101111 -
b101111 .
#48
1%
0&
0'
0(
0)
b110000 -
b110000 .
#49
1)
b110001 -
b110001 .
#50
1(
0)
b110010 -
b110010 .
#51
1)
b110011 -
b110011 .
#52
1'
0(
0)
b110100 -
b110100 .
#53
1)
b110101 -
b110101 .
#54
1(
0)
b110110 -
b110110 .
#55
1)
b110111 -
b110111 .
#56
1&
0'
0(
0)
b111000 -
b111000 .
#57
1)
b111001 -
b111001 .
#58
1(
0)
b111010 -
b111010 .
#59
1)
b111011 -
b111011 .
#60
1'
0(
0)
b111100 -
b111100 .
#61
1)
b111101 -
b111101 .
#62
1(
0)
b111110 -
b111110 .
#63
1)
b111111 -
b111111 .
#64
1#
0$
0%
0&
0'
0(
0)
b1000000 -
b1000000 .
#65
1)
b1000001 -
b1000001 .
#66
1(
0)
b1000010 -
b1000010 .
#67
1)
b1000011 -
b1000011 .
#68
1'
0(
0)
b1000100 -
b1000100 .
#69
1)
b1000101 -
b1000101 .
#70
1(
0)
b1000110 -
b1000110 .
#71
1)
b1000111 -
b1000111 .
#72
1&
0'
0(
0)
b1001000 -
b1001000 .
#73
1)
b1001001 -
b1001001 .
#74
1(
0)
b1001010 -
b1001010 .
#75
1)
b1001011 -
b1001011 .
#76
1'
0(
0)
b1001100 -
b1001100 .
#77
1)
b1001101 -
b1001101 .
#78
1(
0)
b1001110 -
b1001110 .
#79
1)
b1001111 -
b1001111 .
#80
1%
0&
0'
0(
0)
b1010000 -
b1010000 .
#81
1)
b1010001 -
b1010001 .
#82
1(
0)
b1010010 -
b1010010 .
#83
1)
b1010011 -
b1010011 .
#84
1'
0(
0)
b1010100 -
b1010100 .
#85
1)
b1010101 -
b1010101 .
#86
1(
0)
b1010110 -
b1010110 .
#87
1)
b1010111 -
b1010111 .
#88
1&
0'
0(
0)
b1011000 -
b1011000 .
#89
1)
b1011001 -
b1011001 .
#90
1(
0)
b1011010 -
b1011010 .
#91
1)
b1011011 -
b1011011 .
#92
1'
0(
0)
b1011100 -
b1011100 .
#93
1)
b1011101 -
b1011101 .
#94
1(
0)
b1011110 -
b1011110 .
#95
1)
b1011111 -
b1011111 .
#96
1$
0%
0&
0'
0(
0)
b1100000 -
b1100000 .
#97
1)
b1100001 -
b1100001 .
#98
1(
0)
b1100010 -
b1100010 .
#99
1)
b1100011 -
b1100011 .
#100
1'
0(
0)
b1100100 -
b1100100 .
#101
1)
b1100101 -
b1100101 .
#102
1(
0)
b1100110 -
b1100110 .
#103
1)
b1100111 -
b1100111 .
#104
1&
0'
0(
0)
b1101000 -
b1101000 .
#105
1)
b1101001 -
b1101001 .
#106
1(
0)
b1101010 -
b1101010 .
#107
1)
b1101011 -
b1101011 .
#108
1'
0(
0)
b1101100 -
b1101100 .
#109
1)
b1101101 -
b1101101 .
#110
1(
0)
b1101110 -
b1101110 .
#111
1)
b1101111 -
b1101111 .
#112
1%
0&
0'
0(
0)
b1110000 -
b1110000 .
#113
1)
b1110001 -
b1110001 .
#114
1(
0)
b1110010 -
b1110010 .
#115
1)
b1110011 -
b1110011 .
#116
1'
0(
0)
b1110100 -
b1110100 .
#117
1)
b1110101 -
b1110101 .
#118
1(
0)
b1110110 -
b1110110 .
#119
1)
b1110111 -
b1110111 .
#120
1&
0'
0(
0)
b1111000 -
b1111000 .
#121
1)
b1111001 -
b1111001 .
#122
1(
0)
b1111010 -
b1111010 .
#123
1)
b1111011 -
b1111011 .
#124
1'
0(
0)
b1111100 -
b1111100 .
#125
1)
b1111101 -
b1111101 .
#126
1(
0)
b1111110 -
b1111110 .
#127
1)
b1111111 -
b1111111 .
#128
1!
1/
1"
0#
0$
0%
0&
0'
0(
0)
b10000000 -
b10000000 .
#129
1)
b10000001 -
b10000001 .
#130
1(
0)
b10000010 -
b10000010 .
#131
1)
b10000011 -
b10000011 .
#132
1'
0(
0)
b10000100 -
b10000100 .
#133
1)
b10000101 -
b10000101 .
#134
1(
0)
b10000110 -
b10000110 .
#135
1)
b10000111 -
b10000111 .
#136
1&
0'
0(
0)
b10001000 -
b10001000 .
#137
1)
b10001001 -
b10001001 .
#138
1(
0)
b10001010 -
b10001010 .
#139
1)
b10001011 -
b10001011 .
#140
1'
0(
0)
b10001100 -
b10001100 .
#141
1)
b10001101 -
b10001101 .
#142
1(
0)
b10001110 -
b10001110 .
#143
1)
b10001111 -
b10001111 .
#144
1%
0&
0'
0(
0)
b10010000 -
b10010000 .
#145
1)
b10010001 -
b10010001 .
#146
1(
0)
b10010010 -
b10010010 .
#147
1)
b10010011 -
b10010011 .
#148
1'
0(
0)
b10010100 -
b10010100 .
#149
1)
b10010101 -
b10010101 .
#150
1(
0)
b10010110 -
b10010110 .
#151
1)
b10010111 -
b10010111 .
#152
1&
0'
0(
0)
b10011000 -
b10011000 .
#153
1)
b10011001 -
b10011001 .
#154
1(
0)
b10011010 -
b10011010 .
#155
1)
b10011011 -
b10011011 .
#156
1'
0(
0)
b10011100 -
b10011100 .
#157
1)
b10011101 -
b10011101 .
#158
1(
0)
b10011110 -
b10011110 .
#159
1)
b10011111 -
b10011111 .
#160
1$
0%
0&
0'
0(
0)
b10100000 -
b10100000 .
#161
1)
b10100001 -
b10100001 .
#162
1(
0)
b10100010 -
b10100010 .
#163
1)
b10100011 -
b10100011 .
#164
1'
0(
0)
b10100100 -
b10100100 .
#165
1)
b10100101 -
b10100101 .
#166
1(
0)
b10100110 -
b10100110 .
#167
1)
b10100111 -
b10100111 .
#168
1&
0'
0(
0)
b10101000 -
b10101000 .
#169
1)
b10101001 -
b10101001 .
#170
1(
0)
b10101010 -
b10101010 .
#171
1)
b10101011 -
b10101011 .
#172
1'
0(
0)
b10101100 -
b10101100 .
#173
1)
b10101101 -
b10101101 .
#174
1(
0)
b10101110 -
b10101110 .
#175
1)
b10101111 -
b10101111 .
#176
1%
0&
0'
0(
0)
b10110000 -
b10110000 .
#177
1)
b10110001 -
b10110001 .
#178
1(
0)
b10110010 -
b10110010 .
#179
1)
b10110011 -
b10110011 .
#180
1'
0(
0)
b10110100 -
b10110100 .
#181
1)
b10110101 -
b10110101 .
#182
1(
0)
b10110110 -
b10110110 .
#183
1)
b10110111 -
b10110111 .
#184
1&
0'
0(
0)
b10111000 -
b10111000 .
#185
1)
b10111001 -
b10111001 .
#186
1(
0)
b10111010 -
b10111010 .
#187
1)
b10111011 -
b10111011 .
#188
1'
0(
0)
b10111100 -
b10111100 .
#189
1)
b10111101 -
b10111101 .
#190
1(
0)
b10111110 -
b10111110 .
#191
1)
b10111111 -
b10111111 .
#192
1#
0$
0%
0&
0'
0(
0)
b11000000 -
b11000000 .
#193
1)
b11000001 -
b11000001 .
#194
1(
0)
b11000010 -
b11000010 .
#195
1)
b11000011 -
b11000011 .
#196
1'
0(
0)
b11000100 -
b11000100 .
#197
1)
b11000101 -
b11000101 .
#198
1(
0)
b11000110 -
b11000110 .
#199
1)
b11000111 -
b11000111 .
#200
1&
0'
0(
0)
b11001000 -
b11001000 .
#201
1)
b11001001 -
b11001001 .
#202
1(
0)
b11001010 -
b11001010 .
#203
1)
b11001011 -
b11001011 .
#204
1'
0(
0)
b11001100 -
b11001100 .
#205
1)
b11001101 -
b11001101 .
#206
1(
0)
b11001110 -
b11001110 .
#207
1)
b11001111 -
b11001111 .
#208
1%
0&
0'
0(
0)
b11010000 -
b11010000 .
#209
1)
b11010001 -
b11010001 .
#210
1(
0)
b11010010 -
b11010010 .
#211
1)
b11010011 -
b11010011 .
#212
1'
0(
0)
b11010100 -
b11010100 .
#213
1)
b11010101 -
b11010101 .
#214
1(
0)
b11010110 -
b11010110 .
#215
1)
b11010111 -
b11010111 .
#216
1&
0'
0(
0)
b11011000 -
b11011000 .
#217
1)
b11011001 -
b11011001 .
#218
1(
0)
b11011010 -
b11011010 .
#219
1)
b11011011 -
b11011011 .
#220
1'
0(
0)
b11011100 -
b11011100 .
#221
1)
b11011101 -
b11011101 .
#222
1(
0)
b11011110 -
b11011110 .
#223
1)
b11011111 -
b11011111 .
#224
1$
0%
0&
0'
0(
0)
b11100000 -
b11100000 .
#225
1)
b11100001 -
b11100001 .
#226
1(
0)
b11100010 -
b11100010 .
#227
1)
b11100011 -
b11100011 .
#228
1'
0(
0)
b11100100 -
b11100100 .
#229
1)
b11100101 -
b11100101 .
#230
1(
0)
b11100110 -
b11100110 .
#231
1)
b11100111 -
b11100111 .
#232
1&
0'
0(
0)
b11101000 -
b11101000 .
#233
1)
b11101001 -
b11101001 .
#234
1(
0)
b11101010 -
b11101010 .
#235
1)
b11101011 -
b11101011 .
#236
1'
0(
0)
b11101100 -
b11101100 .
#237
1)
b11101101 -
b11101101 .
#238
1(
0)
b11101110 -
b11101110 .
#239
1)
b11101111 -
b11101111 .
#240
1%
0&
0'
0(
0)
b11110000 -
b11110000 .
#241
1)
b11110001 -
b11110001 .
#242
1(
0)
b11110010 -
b11110010 .
#243
1)
b11110011 -
b11110011 .
#244
1'
0(
0)
b11110100 -
b11110100 .
#245
1)
b11110101 -
b11110101 .
#246
1(
0)
b11110110 -
b11110110 .
#247
1)
b11110111 -
b11110111 .
#248
1&
0'
0(
0)
b11111000 -
b11111000 .
#249
1)
b11111001 -
b11111001 .
#250
1(
0)
b11111010 -
b11111010 .
#251
1)
b11111011 -
b11111011 .
#252
1'
0(
0)
b11111100 -
b11111100 .
#253
1)
b11111101 -
b11111101 .
#254
1(
0)
b11111110 -
b11111110 .
#255
1)
b11111111 -
b11111111 .
#256
0!
07
0/
1*
0"
0#
0$
0%
0&
0'
0(
0)
b100000000 -
b100000000 .
#257
1)
b100000001 -
b100000001 .
#258
1(
0)
b100000010 -
b100000010 .
#259
1)
b100000011 -
b100000011 .
#260
1'
0(
0)
b100000100 -
b100000100 .
#261
1)
b100000101 -
b100000101 .
#262
1(
0)
b100000110 -
b100000110 .
#263
1)
b100000111 -
b100000111 .
#264
1&
0'
0(
0)
b100001000 -
b100001000 .
#265
1)
b100001001 -
b100001001 .
#266
1(
0)
b100001010 -
b100001010 .
#267
1)
b100001011 -
b100001011 .
#268
1'
0(
0)
b100001100 -
b100001100 .
#269
1)
b100001101 -
b100001101 .
#270
1(
0)
b100001110 -
b100001110 .
#271
1)
b100001111 -
b100001111 .
#272
1%
0&
0'
0(
0)
b100010000 -
b100010000 .
#273
1)
b100010001 -
b100010001 .
#274
1(
0)
b100010010 -
b100010010 .
#275
1)
b100010011 -
b100010011 .
#276
1'
0(
0)
b100010100 -
b100010100 .
#277
1)
b100010101 -
b100010101 .
#278
1(
0)
b100010110 -
b100010110 .
#279
1)
b100010111 -
b100010111 .
#280
1&
0'
0(
0)
b100011000 -
b100011000 .
#281
1)
b100011001 -
b100011001 .
#282
1(
0)
b100011010 -
b100011010 .
#283
1)
b100011011 -
b100011011 .
#284
1'
0(
0)
b100011100 -
b100011100 .
#285
1)
b100011101 -
b100011101 .
#286
1(
0)
b100011110 -
b100011110 .
#287
1)
b100011111 -
b100011111 .
#288
1$
0%
0&
0'
0(
0)
b100100000 -
b100100000 .
#289
1)
b100100001 -
b100100001 .
#290
1(
0)
b100100010 -
b100100010 .
#291
1)
b100100011 -
b100100011 .
#292
1'
0(
0)
b100100100 -
b100100100 .
#293
1)
b100100101 -
b100100101 .
#294
1(
0)
b100100110 -
b100100110 .
#295
1)
b100100111 -
b100100111 .
#296
1&
0'
0(
0)
b100101000 -
b100101000 .
#297
1)
b100101001 -
b100101001 .
#298
1(
0)
b100101010 -
b100101010 .
#299
1)
b100101011 -
b100101011 .
#300
1'
0(
0)
b100101100 -
b100101100 .
#301
1)
b100101101 -
b100101101 .
#302
1(
0)
b100101110 -
b100101110 .
#303
1)
b100101111 -
b100101111 .
#304
1%
0&
0'
0(
0)
b100110000 -
b100110000 .
#305
1)
b100110001 -
b100110001 .
#306
1(
0)
b100110010 -
b100110010 .
#307
1)
b100110011 -
b100110011 .
#308
1'
0(
0)
b100110100 -
b100110100 .
#309
1)
b100110101 -
b100110101 .
#310
1(
0)
b100110110 -
b100110110 .
#311
1)
b100110111 -
b100110111 .
#312
1&
0'
0(
0)
b100111000 -
b100111000 .
#313
1)
b100111001 -
b100111001 .
#314
1(
0)
b100111010 -
b100111010 .
#315
1)
b100111011 -
b100111011 .
#316
1'
0(
0)
b100111100 -
b100111100 .
#317
1)
b100111101 -
b100111101 .
#318
1(
0)
b100111110 -
b100111110 .
#319
1)
b100111111 -
b100111111 .
#320
1!
10
1#
0$
0%
0&
0'
0(
0)
b101000000 -
b101000000 .
#321
1)
b101000001 -
b101000001 .
#322
1(
0)
b101000010 -
b101000010 .
#323
1)
b101000011 -
b101000011 .
#324
1'
0(
0)
b101000100 -
b101000100 .
#325
1)
b101000101 -
b101000101 .
#326
1(
0)
b101000110 -
b101000110 .
#327
1)
b101000111 -
b101000111 .
#328
1&
0'
0(
0)
b101001000 -
b101001000 .
#329
1)
b101001001 -
b101001001 .
#330
1(
0)
b101001010 -
b101001010 .
#331
1)
b101001011 -
b101001011 .
#332
1'
0(
0)
b101001100 -
b101001100 .
#333
1)
b101001101 -
b101001101 .
#334
1(
0)
b101001110 -
b101001110 .
#335
1)
b101001111 -
b101001111 .
#336
1%
0&
0'
0(
0)
b101010000 -
b101010000 .
#337
1)
b101010001 -
b101010001 .
#338
1(
0)
b101010010 -
b101010010 .
#339
1)
b101010011 -
b101010011 .
#340
1'
0(
0)
b101010100 -
b101010100 .
#341
1)
b101010101 -
b101010101 .
#342
1(
0)
b101010110 -
b101010110 .
#343
1)
b101010111 -
b101010111 .
#344
1&
0'
0(
0)
b101011000 -
b101011000 .
#345
1)
b101011001 -
b101011001 .
#346
1(
0)
b101011010 -
b101011010 .
#347
1)
b101011011 -
b101011011 .
#348
1'
0(
0)
b101011100 -
b101011100 .
#349
1)
b101011101 -
b101011101 .
#350
1(
0)
b101011110 -
b101011110 .
#351
1)
b101011111 -
b101011111 .
#352
1$
0%
0&
0'
0(
0)
b101100000 -
b101100000 .
#353
1)
b101100001 -
b101100001 .
#354
1(
0)
b101100010 -
b101100010 .
#355
1)
b101100011 -
b101100011 .
#356
1'
0(
0)
b101100100 -
b101100100 .
#357
1)
b101100101 -
b101100101 .
#358
1(
0)
b101100110 -
b101100110 .
#359
1)
b101100111 -
b101100111 .
#360
1&
0'
0(
0)
b101101000 -
b101101000 .
#361
1)
b101101001 -
b101101001 .
#362
1(
0)
b101101010 -
b101101010 .
#363
1)
b101101011 -
b101101011 .
#364
1'
0(
0)
b101101100 -
b101101100 .
#365
1)
b101101101 -
b101101101 .
#366
1(
0)
b101101110 -
b101101110 .
#367
1)
b101101111 -
b101101111 .
#368
1%
0&
0'
0(
0)
b101110000 -
b101110000 .
#369
1)
b101110001 -
b101110001 .
#370
1(
0)
b101110010 -
b101110010 .
#371
1)
b101110011 -
b101110011 .
#372
1'
0(
0)
b101110100 -
b101110100 .
#373
1)
b101110101 -
b101110101 .
#374
1(
0)
b101110110 -
b101110110 .
#375
1)
b101110111 -
b101110111 .
#376
1&
0'
0(
0)
b101111000 -
b101111000 .
#377
1)
b101111001 -
b101111001 .
#378
1(
0)
b101111010 -
b101111010 .
#379
1)
b101111011 -
b101111011 .
#380
1'
0(
0)
b101111100 -
b101111100 .
#381
1)
b101111101 -
b101111101 .
#382
1(
0)
b101111110 -
b101111110 .
#383
1)
b101111111 -
b101111111 .
#384
0!
00
1"
0#
0$
0%
0&
0'
0(
0)
b110000000 -
b110000000 .
#385
1)
b110000001 -
b110000001 .
#386
1(
0)
b110000010 -
b110000010 .
#387
1)
b110000011 -
b110000011 .
#388
1'
0(
0)
b110000100 -
b110000100 .
#389
1)
b110000101 -
b110000101 .
#390
1(
0)
b110000110 -
b110000110 .
#391
1)
b110000111 -
b110000111 .
#392
1&
0'
0(
0)
b110001000 -
b110001000 .
#393
1)
b110001001 -
b110001001 .
#394
1(
0)
b110001010 -
b110001010 .
#395
1)
b110001011 -
b110001011 .
#396
1'
0(
0)
b110001100 -
b110001100 .
#397
1)
b110001101 -
b110001101 .
#398
1(
0)
b110001110 -
b110001110 .
#399
1)
b110001111 -
b110001111 .
#400
1%
0&
0'
0(
0)
b110010000 -
b110010000 .
#401
1)
b110010001 -
b110010001 .
#402
1(
0)
b110010010 -
b110010010 .
#403
1)
b110010011 -
b110010011 .
#404
1'
0(
0)
b110010100 -
b110010100 .
#405
1)
b110010101 -
b110010101 .
#406
1(
0)
b110010110 -
b110010110 .
#407
1)
b110010111 -
b110010111 .
#408
1&
0'
0(
0)
b110011000 -
b110011000 .
#409
1)
b110011001 -
b110011001 .
#410
1(
0)
b110011010 -
b110011010 .
#411
1)
b110011011 -
b110011011 .
#412
1'
0(
0)
b110011100 -
b110011100 .
#413
1)
b110011101 -
b110011101 .
#414
1(
0)
b110011110 -
b110011110 .
#415
1)
b110011111 -
b110011111 .
#416
1$
0%
0&
0'
0(
0)
b110100000 -
b110100000 .
#417
1)
b110100001 -
b110100001 .
#418
1(
0)
b110100010 -
b110100010 .
#419
1)
b110100011 -
b110100011 .
#420
1'
0(
0)
b110100100 -
b110100100 .
#421
1)
b110100101 -
b110100101 .
#422
1(
0)
b110100110 -
b110100110 .
#423
1)
b110100111 -
b110100111 .
#424
1&
0'
0(
0)
b110101000 -
b110101000 .
#425
1)
b110101001 -
b110101001 .
#426
1(
0)
b110101010 -
b110101010 .
#427
1)
b110101011 -
b110101011 .
#428
1'
0(
0)
b110101100 -
b110101100 .
#429
1)
b110101101 -
b110101101 .
#430
1(
0)
b110101110 -
b110101110 .
#431
1)
b110101111 -
b110101111 .
#432
1%
0&
0'
0(
0)
b110110000 -
b110110000 .
#433
1)
b110110001 -
b110110001 .
#434
1(
0)
b110110010 -
b110110010 .
#435
1)
b110110011 -
b110110011 .
#436
1'
0(
0)
b110110100 -
b110110100 .
#437
1)
b110110101 -
b110110101 .
#438
1(
0)
b110110110 -
b110110110 .
#439
1)
b110110111 -
b110110111 .
#440
1&
0'
0(
0)
b110111000 -
b110111000 .
#441
1)
b110111001 -
b110111001 .
#442
1(
0)
b110111010 -
b110111010 .
#443
1)
b110111011 -
b110111011 .
#444
1'
0(
0)
b110111100 -
b110111100 .
#445
1)
b110111101 -
b110111101 .
#446
1(
0)
b110111110 -
b110111110 .
#447
1)
b110111111 -
b110111111 .
#448
1!
10
1#
0$
0%
0&
0'
0(
0)
b111000000 -
b111000000 .
#449
1)
b111000001 -
b111000001 .
#450
1(
0)
b111000010 -
b111000010 .
#451
1)
b111000011 -
b111000011 .
#452
1'
0(
0)
b111000100 -
b111000100 .
#453
1)
b111000101 -
b111000101 .
#454
1(
0)
b111000110 -
b111000110 .
#455
1)
b111000111 -
b111000111 .
#456
1&
0'
0(
0)
b111001000 -
b111001000 .
#457
1)
b111001001 -
b111001001 .
#458
1(
0)
b111001010 -
b111001010 .
#459
1)
b111001011 -
b111001011 .
#460
1'
0(
0)
b111001100 -
b111001100 .
#461
1)
b111001101 -
b111001101 .
#462
1(
0)
b111001110 -
b111001110 .
#463
1)
b111001111 -
b111001111 .
#464
1%
0&
0'
0(
0)
b111010000 -
b111010000 .
#465
1)
b111010001 -
b111010001 .
#466
1(
0)
b111010010 -
b111010010 .
#467
1)
b111010011 -
b111010011 .
#468
1'
0(
0)
b111010100 -
b111010100 .
#469
1)
b111010101 -
b111010101 .
#470
1(
0)
b111010110 -
b111010110 .
#471
1)
b111010111 -
b111010111 .
#472
1&
0'
0(
0)
b111011000 -
b111011000 .
#473
1)
b111011001 -
b111011001 .
#474
1(
0)
b111011010 -
b111011010 .
#475
1)
b111011011 -
b111011011 .
#476
1'
0(
0)
b111011100 -
b111011100 .
#477
1)
b111011101 -
b111011101 .
#478
1(
0)
b111011110 -
b111011110 .
#479
1)
b111011111 -
b111011111 .
#480
1$
0%
0&
0'
0(
0)
b111100000 -
b111100000 .
#481
1)
b111100001 -
b111100001 .
#482
1(
0)
b111100010 -
b111100010 .
#483
1)
b111100011 -
b111100011 .
#484
1'
0(
0)
b111100100 -
b111100100 .
#485
1)
b111100101 -
b111100101 .
#486
1(
0)
b111100110 -
b111100110 .
#487
1)
b111100111 -
b111100111 .
#488
1&
0'
0(
0)
b111101000 -
b111101000 .
#489
1)
b111101001 -
b111101001 .
#490
1(
0)
b111101010 -
b111101010 .
#491
1)
b111101011 -
b111101011 .
#492
1'
0(
0)
b111101100 -
b111101100 .
#493
1)
b111101101 -
b111101101 .
#494
1(
0)
b111101110 -
b111101110 .
#495
1)
b111101111 -
b111101111 .
#496
1%
0&
0'
0(
0)
b111110000 -
b111110000 .
#497
1)
b111110001 -
b111110001 .
#498
1(
0)
b111110010 -
b111110010 .
#499
1)
b111110011 -
b111110011 .
#500
1'
0(
0)
b111110100 -
b111110100 .
#501
1)
b111110101 -
b111110101 .
#502
1(
0)
b111110110 -
b111110110 .
#503
1)
b111110111 -
b111110111 .
#504
1&
0'
0(
0)
b111111000 -
b111111000 .
#505
1)
b111111001 -
b111111001 .
#506
1(
0)
b111111010 -
b111111010 .
#507
1)
b111111011 -
b111111011 .
#508
1'
0(
0)
b111111100 -
b111111100 .
#509
1)
b111111101 -
b111111101 .
#510
1(
0)
b111111110 -
b111111110 .
#511
1)
b111111111 -
b111111111 .
#512
0!
08
17
00
1+
0*
0"
0#
0$
0%
0&
0'
0(
0)
b1000000000 -
b1000000000 .
#513
1)
b1000000001 -
b1000000001 .
#514
1(
0)
b1000000010 -
b1000000010 .
#515
1)
b1000000011 -
b1000000011 .
#516
1'
0(
0)
b1000000100 -
b1000000100 .
#517
1)
b1000000101 -
b1000000101 .
#518
1(
0)
b1000000110 -
b1000000110 .
#519
1)
b1000000111 -
b1000000111 .
#520
1&
0'
0(
0)
b1000001000 -
b1000001000 .
#521
1)
b1000001001 -
b1000001001 .
#522
1(
0)
b1000001010 -
b1000001010 .
#523
1)
b1000001011 -
b1000001011 .
#524
1'
0(
0)
b1000001100 -
b1000001100 .
#525
1)
b1000001101 -
b1000001101 .
#526
1(
0)
b1000001110 -
b1000001110 .
#527
1)
b1000001111 -
b1000001111 .
#528
1%
0&
0'
0(
0)
b1000010000 -
b1000010000 .
#529
1)
b1000010001 -
b1000010001 .
#530
1(
0)
b1000010010 -
b1000010010 .
#531
1)
b1000010011 -
b1000010011 .
#532
1'
0(
0)
b1000010100 -
b1000010100 .
#533
1)
b1000010101 -
b1000010101 .
#534
1(
0)
b1000010110 -
b1000010110 .
#535
1)
b1000010111 -
b1000010111 .
#536
1&
0'
0(
0)
b1000011000 -
b1000011000 .
#537
1)
b1000011001 -
b1000011001 .
#538
1(
0)
b1000011010 -
b1000011010 .
#539
1)
b1000011011 -
b1000011011 .
#540
1'
0(
0)
b1000011100 -
b1000011100 .
#541
1)
b1000011101 -
b1000011101 .
#542
1(
0)
b1000011110 -
b1000011110 .
#543
1)
b1000011111 -
b1000011111 .
#544
1!
11
1$
0%
0&
0'
0(
0)
b1000100000 -
b1000100000 .
#545
1)
b1000100001 -
b1000100001 .
#546
1(
0)
b1000100010 -
b1000100010 .
#547
1)
b1000100011 -
b1000100011 .
#548
1'
0(
0)
b1000100100 -
b1000100100 .
#549
1)
b1000100101 -
b1000100101 .
#550
1(
0)
b1000100110 -
b1000100110 .
#551
1)
b1000100111 -
b1000100111 .
#552
1&
0'
0(
0)
b1000101000 -
b1000101000 .
#553
1)
b1000101001 -
b1000101001 .
#554
1(
0)
b1000101010 -
b1000101010 .
#555
1)
b1000101011 -
b1000101011 .
#556
1'
0(
0)
b1000101100 -
b1000101100 .
#557
1)
b1000101101 -
b1000101101 .
#558
1(
0)
b1000101110 -
b1000101110 .
#559
1)
b1000101111 -
b1000101111 .
#560
1%
0&
0'
0(
0)
b1000110000 -
b1000110000 .
#561
1)
b1000110001 -
b1000110001 .
#562
1(
0)
b1000110010 -
b1000110010 .
#563
1)
b1000110011 -
b1000110011 .
#564
1'
0(
0)
b1000110100 -
b1000110100 .
#565
1)
b1000110101 -
b1000110101 .
#566
1(
0)
b1000110110 -
b1000110110 .
#567
1)
b1000110111 -
b1000110111 .
#568
1&
0'
0(
0)
b1000111000 -
b1000111000 .
#569
1)
b1000111001 -
b1000111001 .
#570
1(
0)
b1000111010 -
b1000111010 .
#571
1)
b1000111011 -
b1000111011 .
#572
1'
0(
0)
b1000111100 -
b1000111100 .
#573
1)
b1000111101 -
b1000111101 .
#574
1(
0)
b1000111110 -
b1000111110 .
#575
1)
b1000111111 -
b1000111111 .
#576
0!
01
1#
0$
0%
0&
0'
0(
0)
b1001000000 -
b1001000000 .
#577
1)
b1001000001 -
b1001000001 .
#578
1(
0)
b1001000010 -
b1001000010 .
#579
1)
b1001000011 -
b1001000011 .
