ACT6/ACT6_DF.v
module ACT6_DF(D, B, Z, X, Y);
input Z, X, Y;
output D, B;
assign D = (Z ^ (X ^ Y));
assign B = (~(X ^ Y) & Z) | (~X & Y);
endmodule

ACT6/ACT6_DF_tb.v
`include "ACT6_DF.v"
module ACT6_DF_tb;
	reg Z, X, Y;
	wire D, B;
	ACT6_DF Instance0(D, B, Z, X, Y);
initial begin
	Z = 0; X = 0; Y = 0;
 #1	Z = 1; X = 0; Y = 0;
 #1	Z = 0; X = 0; Y = 1;
 #1	Z = 1; X = 0; Y = 1;
 #1	Z = 0; X = 1; Y = 0;
 #1	Z = 1; X = 1; Y = 0;
 #1	Z = 0; X = 1; Y = 1;
 #1	Z = 1; X = 1; Y = 1;
 #1;
end
initial begin
	$monitor("%t | Z = %d | X = %d | Y = %d | B = %d | D = %d", $time, Z, X, Y, B, D);
	$dumpfile("ACT6DFF.vcd");
	$dumpvars();
end
	
	
endmodule

ACT6/ACT6DFF.vcd
$date
	Tue Oct 28 09:38:46 2025
$end
$version
	Icarus Verilog
$end
$timescale
	1s
$end
$scope module ACT6_DF_tb $end
$var wire 1 ! D $end
$var wire 1 " B $end
$var reg 1 # X $end
$var reg 1 $ Y $end
$var reg 1 % Z $end
$scope module Instance0 $end
$var wire 1 " B $end
$var wire 1 ! D $end
$var wire 1 # X $end
$var wire 1 $ Y $end
$var wire 1 % Z $end
$upscope $end
$upscope $end
$enddefinitions $end
$comment Show the parameter values. $end
$dumpall
$end
#0
$dumpvars
0%
0$
0#
0"
0!
$end
#1
1"
1!
1%
#2
1!
1$
0%
#3
0!
1%
#4
0"
1!
0$
1#
0%
#5
0!
1%
#6
0!
1$
0%
#7
1"
1!
1%
