ACT6/ACT6_GL.v
module ACT6_GL(D, B, Z, X, Y);
input Z, X, Y;
output D, B;
wire XORw1, NOTw2, ANDw3, NOTw4, ANDw5;
xor x1(D, Z, XORw1);
xor x2(XORw1, X, Y);
not n1(NOTw2, X);
and a1(ANDw3, NOTw2, Y);
not n2(NOTw4, XORw1);
and a2(ANDw5, NOTw4, Z);
or o1(B, ANDw5, ANDw3);
endmodule

ACT6/ACT6_GL_tb.v
`include "ACT6_GL.v"
module ACT6_GL_tb;
	reg Z, X, Y;
	wire D, B;
	ACT6_GL Instance0(D, B, Z, X, Y);
initial begin
	Z = 0; X = 0; Y = 0;
 #1	Z = 1; X = 0; Y = 0;
 #1	Z = 0; X = 0; Y = 1;
 #1	Z = 1; X = 0; Y = 1;
 #1	Z = 0; X = 1; Y = 0;
 #1	Z = 1; X = 1; Y = 0;
 #1	Z = 0; X = 1; Y = 1;
 #1	Z = 1; X = 1; Y = 1;
 #1;
end
initial begin
	$monitor("%t | Z = %d | X = %d | Y = %d | B = %d | D = %d", $time, Z, X, Y, B, D);
	$dumpfile("ACT6.vcd");
	$dumpvars();
end
	
	
endmodule

ACT6/ACT6.vcd
$date
	Tue Oct 28 09:36:52 2025
$end
$version
	Icarus Verilog
$end
$timescale
	1s
$end
$scope module ACT6_GL_tb $end
$var wire 1 ! D $end
$var wire 1 " B $end
$var reg 1 # X $end
$var reg 1 $ Y $end
$var reg 1 % Z $end
$scope module Instance0 $end
$var wire 1 & ANDw3 $end
$var wire 1 ' ANDw5 $end
$var wire 1 " B $end
$var wire 1 ! D $end
$var wire 1 ( NOTw2 $end
$var wire 1 ) NOTw4 $end
$var wire 1 # X $end
$var wire 1 * XORw1 $end
$var wire 1 $ Y $end
$var wire 1 % Z $end
$upscope $end
$upscope $end
$enddefinitions $end
$comment Show the parameter values. $end
$dumpall
$end
#0
$dumpvars
0*
1)
1(
0'
0&
0%
0$
0#
0"
0!
$end
#1
1"
1!
1'
1%
#2
0)
1*
1&
1!
0'
1$
0%
#3
0!
1%
#4
0"
0&
0(
1!
0$
1#
0%
#5
0!
1%
#6
1)
0*
0!
1$
0%
#7
1"
1!
1'
1%
