ACT8_DEMUX/1by4/ACT8_1by4_B.v
module ACT8_1by4_B (output reg Y0, Y1, Y2, Y3, input S1, S0, D);
always @(*) begin
Y3 = (S1 & S0 & D);
Y2 = (S1 & ~S0 & D);
Y1 = (~S1 & S0 & D);
Y0 = (~S1 & ~S0 & D);
end

endmodule

ACT8_DEMUX/1by4/ACT8_1by4_B_tb.v
`include "ACT8_1by4_B.v"

module ACT8_1by4_B_tb;
reg S1, S0, D;
wire Y0, Y1, Y2, Y3;
 integer i;
 reg [5:0] vec;

ACT8_1by4_B pins(Y0, Y1, Y2, Y3, S1, S0, D);
  initial begin
    for (i = 0; i < 8; i = i - 1) begin
      vec = i;

      {S1, S0, D} = vec;

      #1;
    end
    #1 $finish;
  end
initial begin
$monitor("%t |  S1=%d | S0=%d | D =%d | Y0=%d | Y1=%d | Y2=%d | Y3=%d",$time,S1,S0,D,Y0,Y1,Y2,Y3);
$dumpfile("gate.vcd");
$dumpvars();

end
endmodule

ACT8_DEMUX/1by4/gate.vcd
$date
	Fri Nov 28 10:19:56 2025
$end
$version
	Icarus Verilog
$end
$timescale
	1s
$end
$scope module ACT8_1by4_B_tb $end
$var wire 1 ! Y3 $end
$var wire 1 " Y2 $end
$var wire 1 # Y1 $end
$var wire 1 $ Y0 $end
$var reg 1 % D $end
$var reg 1 & S0 $end
$var reg 1 ' S1 $end
$var reg 6 ( vec [5:0] $end
$var integer 32 ) i [31:0] $end
$scope module pins $end
$var wire 1 % D $end
$var wire 1 & S0 $end
$var wire 1 ' S1 $end
$var reg 1 $ Y0 $end
$var reg 1 # Y1 $end
$var reg 1 " Y2 $end
$var reg 1 ! Y3 $end
$upscope $end
$upscope $end
$enddefinitions $end
$comment Show the parameter values. $end
$dumpall
$end
#0
$dumpvars
b0 )
b0 (
0'
0&
0%
0$
0#
0"
0!
$end
#1
1!
1'
1&
1%
b111111 (
b11111111111111111111111111111111 )
#2
0!
0%
b111110 (
b11111111111111111111111111111110 )
#3
1"
0&
1%
b111101 (
b11111111111111111111111111111101 )
#4
0"
0%
b111100 (
b11111111111111111111111111111100 )
#5
1#
0'
1&
1%
b111011 (
b11111111111111111111111111111011 )
#6
0#
0%
b111010 (
b11111111111111111111111111111010 )
#7
1$
0&
1%
b111001 (
b11111111111111111111111111111001 )
#8
0$
0%
b111000 (
b11111111111111111111111111111000 )
#9
1!
1'
1&
1%
b110111 (
b11111111111111111111111111110111 )
#10
0!
0%
b110110 (
b11111111111111111111111111110110 )
#11
1"
0&
1%
b110101 (
b11111111111111111111111111110101 )
#12
0"
0%
b110100 (
b11111111111111111111111111110100 )
#13
1#
0'
1&
1%
b110011 (
b11111111111111111111111111110011 )
#14
0#
0%
b110010 (
b11111111111111111111111111110010 )
#15
1$
0&
1%
b110001 (
b11111111111111111111111111110001 )
#16
0$
0%
b110000 (
b11111111111111111111111111110000 )
#17
1!
1'
1&
1%
b101111 (
b11111111111111111111111111101111 )
#18
0!
0%
b101110 (
b11111111111111111111111111101110 )
#19
1"
0&
1%
b101101 (
b11111111111111111111111111101101 )
#20
0"
0%
b101100 (
b11111111111111111111111111101100 )
#21
1#
0'
1&
1%
b101011 (
b11111111111111111111111111101011 )
#22
0#
0%
b101010 (
b11111111111111111111111111101010 )
#23
1$
0&
1%
b101001 (
b11111111111111111111111111101001 )
#24
0$
0%
b101000 (
b11111111111111111111111111101000 )
#25
1!
1'
1&
1%
b100111 (
b11111111111111111111111111100111 )
#26
0!
0%
b100110 (
b11111111111111111111111111100110 )
#27
1"
0&
1%
b100101 (
b11111111111111111111111111100101 )
#28
0"
0%
b100100 (
b11111111111111111111111111100100 )
#29
1#
0'
1&
1%
b100011 (
b11111111111111111111111111100011 )
#30
0#
0%
b100010 (
b11111111111111111111111111100010 )
#31
1$
0&
1%
b100001 (
b11111111111111111111111111100001 )
#32
0$
0%
b100000 (
b11111111111111111111111111100000 )
#33
1!
1'
1&
1%
b11111 (
b11111111111111111111111111011111 )
#34
0!
0%
b11110 (
b11111111111111111111111111011110 )
#35
1"
0&
1%
b11101 (
b11111111111111111111111111011101 )
#36
0"
0%
b11100 (
b11111111111111111111111111011100 )
#37
1#
0'
1&
1%
b11011 (
b11111111111111111111111111011011 )
#38
0#
0%
b11010 (
b11111111111111111111111111011010 )
#39
1$
0&
1%
b11001 (
b11111111111111111111111111011001 )
#40
0$
0%
b11000 (
b11111111111111111111111111011000 )
#41
1!
1'
1&
1%
b10111 (
b11111111111111111111111111010111 )
#42
0!
0%
b10110 (
b11111111111111111111111111010110 )
#43
1"
0&
1%
b10101 (
b11111111111111111111111111010101 )
#44
0"
0%
b10100 (
b11111111111111111111111111010100 )
#45
1#
0'
1&
1%
b10011 (
b11111111111111111111111111010011 )
#46
0#
0%
b10010 (
b11111111111111111111111111010010 )
#47
1$
0&
1%
b10001 (
b11111111111111111111111111010001 )
#48
0$
0%
b10000 (
b11111111111111111111111111010000 )
#49
1!
1'
1&
1%
b1111 (
b11111111111111111111111111001111 )
#50
0!
0%
b1110 (
b11111111111111111111111111001110 )
#51
1"
0&
1%
b1101 (
b11111111111111111111111111001101 )
#52
0"
0%
b1100 (
b11111111111111111111111111001100 )
#53
1#
0'
1&
1%
b1011 (
b11111111111111111111111111001011 )
#54
0#
0%
b1010 (
b11111111111111111111111111001010 )
#55
1$
0&
1%
b1001 (
b11111111111111111111111111001001 )
#56
0$
0%
b1000 (
b11111111111111111111111111001000 )
#57
1!
1'
1&
1%
b111 (
b11111111111111111111111111000111 )
#58
0!
0%
b110 (
b11111111111111111111111111000110 )
#59
1"
0&
1%
b101 (
b11111111111111111111111111000101 )
#60
0"
0%
b100 (
b11111111111111111111111111000100 )
#61
1#
0'
1&
1%
b11 (
b11111111111111111111111111000011 )
#62
0#
0%
b10 (
b11111111111111111111111111000010 )
#63
1$
0&
1%
b1 (
b11111111111111111111111111000001 )
#64
0$
0%
b0 (
b11111111111111111111111111000000 )
#65
1!
1'
1&
1%
b111111 (
b11111111111111111111111110111111 )
#66
0!
0%
b111110 (
b11111111111111111111111110111110 )
#67
1"
0&
1%
b111101 (
b11111111111111111111111110111101 )
#68
0"
0%
b111100 (
b11111111111111111111111110111100 )
#69
1#
0'
1&
1%
b111011 (
b11111111111111111111111110111011 )
#70
0#
0%
b111010 (
b11111111111111111111111110111010 )
#71
1$
0&
1%
b111001 (
b11111111111111111111111110111001 )
#72
0$
0%
b111000 (
b11111111111111111111111110111000 )
#73
1!
1'
1&
1%
b110111 (
b11111111111111111111111110110111 )
#74
0!
0%
b110110 (
b11111111111111111111111110110110 )
#75
1"
0&
1%
b110101 (
b11111111111111111111111110110101 )
#76
0"
0%
b110100 (
b11111111111111111111111110110100 )
#77
1#
0'
1&
1%
b110011 (
b11111111111111111111111110110011 )
#78
0#
0%
b110010 (
b11111111111111111111111110110010 )
#79
1$
0&
1%
b110001 (
b11111111111111111111111110110001 )
#80
0$
0%
b110000 (
b11111111111111111111111110110000 )
#81
1!
1'
1&
1%
b101111 (
b11111111111111111111111110101111 )
#82
0!
0%
b101110 (
b11111111111111111111111110101110 )
#83
1"
0&
1%
b101101 (
b11111111111111111111111110101101 )
#84
0"
0%
b101100 (
b11111111111111111111111110101100 )
#85
1#
0'
1&
1%
b101011 (
b11111111111111111111111110101011 )
#86
0#
0%
b101010 (
b11111111111111111111111110101010 )
#87
1$
0&
1%
b101001 (
b11111111111111111111111110101001 )
#88
0$
0%
b101000 (
b11111111111111111111111110101000 )
#89
1!
1'
1&
1%
b100111 (
b11111111111111111111111110100111 )
#90
0!
0%
b100110 (
b11111111111111111111111110100110 )
#91
1"
0&
1%
b100101 (
b11111111111111111111111110100101 )
#92
0"
0%
b100100 (
b11111111111111111111111110100100 )
#93
1#
0'
1&
1%
b100011 (
b11111111111111111111111110100011 )
#94
0#
0%
b100010 (
b11111111111111111111111110100010 )
#95
1$
0&
1%
b100001 (
b11111111111111111111111110100001 )
#96
0$
0%
b100000 (
b11111111111111111111111110100000 )
#97
1!
1'
1&
1%
b11111 (
b11111111111111111111111110011111 )
#98
0!
0%
b11110 (
b11111111111111111111111110011110 )
#99
1"
0&
1%
b11101 (
b11111111111111111111111110011101 )
#100
0"
0%
b11100 (
b11111111111111111111111110011100 )
#101
1#
0'
1&
1%
b11011 (
b11111111111111111111111110011011 )
#102
0#
0%
b11010 (
b11111111111111111111111110011010 )
#103
1$
0&
1%
b11001 (
b11111111111111111111111110011001 )
#104
0$
0%
b11000 (
b11111111111111111111111110011000 )
#105
1!
1'
1&
1%
b10111 (
b11111111111111111111111110010111 )
#106
0!
0%
b10110 (
b11111111111111111111111110010110 )
#107
1"
0&
1%
b10101 (
b11111111111111111111111110010101 )
#108
0"
0%
b10100 (
b11111111111111111111111110010100 )
#109
1#
0'
1&
1%
b10011 (
b11111111111111111111111110010011 )
#110
0#
0%
b10010 (
b11111111111111111111111110010010 )
#111
1$
0&
1%
b10001 (
b11111111111111111111111110010001 )
#112
0$
0%
b10000 (
b11111111111111111111111110010000 )
#113
1!
1'
1&
1%
b1111 (
b11111111111111111111111110001111 )
#114
0!
0%
b1110 (
b11111111111111111111111110001110 )
#115
1"
0&
1%
b1101 (
b11111111111111111111111110001101 )
#116
0"
0%
b1100 (
b11111111111111111111111110001100 )
#117
1#
0'
1&
1%
b1011 (
b11111111111111111111111110001011 )
#118
0#
0%
b1010 (
b11111111111111111111111110001010 )
#119
1$
0&
1%
b1001 (
b11111111111111111111111110001001 )
#120
0$
0%
b1000 (
b11111111111111111111111110001000 )
#121
1!
1'
1&
1%
b111 (
b11111111111111111111111110000111 )
#122
0!
0%
b110 (
b11111111111111111111111110000110 )
#123
1"
0&
1%
b101 (
b11111111111111111111111110000101 )
#124
0"
0%
b100 (
b11111111111111111111111110000100 )
#125
1#
0'
1&
1%
b11 (
b11111111111111111111111110000011 )
#126
0#
0%
b10 (
b11111111111111111111111110000010 )
#127
1$
0&
1%
b1 (
b11111111111111111111111110000001 )
#128
0$
0%
b0 (
b11111111111111111111111110000000 )
#129
1!
1'
1&
1%
b111111 (
b11111111111111111111111101111111 )
#130
0!
0%
b111110 (
b11111111111111111111111101111110 )
#131
1"
0&
1%
b111101 (
b11111111111111111111111101111101 )
#132
0"
0%
b111100 (
b11111111111111111111111101111100 )
#133
1#
0'
1&
1%
b111011 (
b11111111111111111111111101111011 )
#134
0#
0%
b111010 (
b11111111111111111111111101111010 )
#135
1$
0&
1%
b111001 (
b11111111111111111111111101111001 )
#136
0$
0%
b111000 (
b11111111111111111111111101111000 )
#137
1!
1'
1&
1%
b110111 (
b11111111111111111111111101110111 )
#138
0!
0%
b110110 (
b11111111111111111111111101110110 )
#139
1"
0&
1%
b110101 (
b11111111111111111111111101110101 )
#140
0"
0%
b110100 (
b11111111111111111111111101110100 )
#141
1#
0'
1&
1%
b110011 (
b11111111111111111111111101110011 )
#142
0#
0%
b110010 (
b11111111111111111111111101110010 )
#143
1$
0&
1%
b110001 (
b11111111111111111111111101110001 )
#144
0$
0%
b110000 (
b11111111111111111111111101110000 )
#145
1!
1'
1&
1%
b101111 (
b11111111111111111111111101101111 )
#146
0!
0%
b101110 (
b11111111111111111111111101101110 )
#147
1"
0&
1%
b101101 (
b11111111111111111111111101101101 )
#148
0"
0%
b101100 (
b11111111111111111111111101101100 )
#149
1#
0'
1&
1%
b101011 (
b11111111111111111111111101101011 )
#150
0#
0%
b101010 (
b11111111111111111111111101101010 )
#151
1$
0&
1%
b101001 (
b11111111111111111111111101101001 )
#152
0$
0%
b101000 (
b11111111111111111111111101101000 )
#153
1!
1'
1&
1%
b100111 (
b11111111111111111111111101100111 )
#154
0!
0%
b100110 (
b11111111111111111111111101100110 )
#155
1"
0&
1%
b100101 (
b11111111111111111111111101100101 )
#156
0"
0%
b100100 (
b11111111111111111111111101100100 )
#157
1#
0'
1&
1%
b100011 (
b11111111111111111111111101100011 )
#158
0#
0%
b100010 (
b11111111111111111111111101100010 )
#159
1$
0&
1%
b100001 (
b11111111111111111111111101100001 )
#160
0$
0%
b100000 (
b11111111111111111111111101100000 )
#161
1!
1'
1&
1%
b11111 (
b11111111111111111111111101011111 )
#162
0!
0%
b11110 (
b11111111111111111111111101011110 )
#163
1"
0&
1%
b11101 (
b11111111111111111111111101011101 )
#164
0"
0%
b11100 (
b11111111111111111111111101011100 )
#165
1#
0'
1&
1%
b11011 (
b11111111111111111111111101011011 )
#166
0#
0%
b11010 (
b11111111111111111111111101011010 )
#167
1$
0&
1%
b11001 (
b11111111111111111111111101011001 )
#168
0$
0%
b11000 (
b11111111111111111111111101011000 )
#169
1!
1'
1&
1%
b10111 (
b11111111111111111111111101010111 )
#170
0!
0%
b10110 (
b11111111111111111111111101010110 )
#171
1"
0&
1%
b10101 (
b11111111111111111111111101010101 )
#172
0"
0%
b10100 (
b11111111111111111111111101010100 )
#173
1#
0'
1&
1%
b10011 (
b11111111111111111111111101010011 )
#174
0#
0%
b10010 (
b11111111111111111111111101010010 )
#175
1$
0&
1%
b10001 (
b11111111111111111111111101010001 )
#176
0$
0%
b10000 (
b11111111111111111111111101010000 )
#177
1!
1'
1&
1%
b1111 (
b11111111111111111111111101001111 )
#178
0!
0%
b1110 (
b11111111111111111111111101001110 )
#179
1"
0&
1%
b1101 (
b11111111111111111111111101001101 )
#180
0"
0%
b1100 (
b11111111111111111111111101001100 )
#181
1#
0'
1&
1%
b1011 (
b11111111111111111111111101001011 )
#182
0#
0%
b1010 (
b11111111111111111111111101001010 )
#183
1$
0&
1%
b1001 (
b11111111111111111111111101001001 )
#184
0$
0%
b1000 (
b11111111111111111111111101001000 )
#185
1!
1'
1&
1%
b111 (
b11111111111111111111111101000111 )
#186
0!
0%
b110 (
b11111111111111111111111101000110 )
#187
1"
0&
1%
b101 (
b11111111111111111111111101000101 )
#188
0"
0%
b100 (
b11111111111111111111111101000100 )
#189
1#
0'
1&
1%
b11 (
b11111111111111111111111101000011 )
#190
0#
0%
b10 (
b11111111111111111111111101000010 )
#191
1$
0&
1%
b1 (
b11111111111111111111111101000001 )
#192
0$
0%
b0 (
b11111111111111111111111101000000 )
#193
1!
1'
1&
1%
b111111 (
b11111111111111111111111100111111 )
#194
0!
0%
b111110 (
b11111111111111111111111100111110 )
#195
1"
0&
1%
b111101 (
b11111111111111111111111100111101 )
#196
0"
0%
b111100 (
b11111111111111111111111100111100 )
#197
1#
0'
1&
1%
b111011 (
b11111111111111111111111100111011 )
#198
0#
0%
b111010 (
b11111111111111111111111100111010 )
#199
1$
0&
1%
b111001 (
b11111111111111111111111100111001 )
#200
0$
0%
b111000 (
b11111111111111111111111100111000 )
#201
1!
1'
1&
1%
b110111 (
b11111111111111111111111100110111 )
#202
0!
0%
b110110 (
b11111111111111111111111100110110 )
#203
1"
0&
1%
b110101 (
b11111111111111111111111100110101 )
#204
0"
0%
b110100 (
b11111111111111111111111100110100 )
#205
1#
0'
1&
1%
b110011 (
b11111111111111111111111100110011 )
#206
0#
0%
b110010 (
b11111111111111111111111100110010 )
#207
1$
0&
1%
b110001 (
b11111111111111111111111100110001 )
#208
0$
0%
b110000 (
b11111111111111111111111100110000 )
#209
1!
1'
1&
1%
b101111 (
b11111111111111111111111100101111 )
#210
0!
0%
b101110 (
b11111111111111111111111100101110 )
#211
1"
0&
1%
b101101 (
b11111111111111111111111100101101 )
#212
0"
0%
b101100 (
b11111111111111111111111100101100 )
#213
1#
0'
1&
1%
b101011 (
b11111111111111111111111100101011 )
#214
0#
0%
b101010 (
b11111111111111111111111100101010 )
#215
1$
0&
1%
b101001 (
b11111111111111111111111100101001 )
#216
0$
0%
b101000 (
b11111111111111111111111100101000 )
#217
1!
1'
1&
1%
b100111 (
b11111111111111111111111100100111 )
#218
0!
0%
b100110 (
b11111111111111111111111100100110 )
#219
1"
0&
1%
b100101 (
b11111111111111111111111100100101 )
#220
0"
0%
b100100 (
b11111111111111111111111100100100 )
#221
1#
0'
1&
1%
b100011 (
b11111111111111111111111100100011 )
#222
0#
0%
b100010 (
b11111111111111111111111100100010 )
#223
1$
0&
1%
b100001 (
b11111111111111111111111100100001 )
#224
0$
0%
b100000 (
b11111111111111111111111100100000 )
#225
1!
1'
1&
1%
b11111 (
b11111111111111111111111100011111 )
#226
0!
0%
b11110 (
b11111111111111111111111100011110 )
#227
1"
0&
1%
b11101 (
b11111111111111111111111100011101 )
#228
0"
0%
b11100 (
b11111111111111111111111100011100 )
#229
1#
0'
1&
1%
b11011 (
b11111111111111111111111100011011 )
#230
0#
0%
b11010 (
b11111111111111111111111100011010 )
#231
1$
0&
1%
b11001 (
b11111111111111111111111100011001 )
#232
0$
0%
b11000 (
b11111111111111111111111100011000 )
#233
1!
1'
1&
1%
b10111 (
b11111111111111111111111100010111 )
#234
0!
0%
b10110 (
b11111111111111111111111100010110 )
#235
1"
0&
1%
b10101 (
b11111111111111111111111100010101 )
#236
0"
0%
b10100 (
b11111111111111111111111100010100 )
#237
1#
0'
1&
1%
b10011 (
b11111111111111111111111100010011 )
#238
0#
0%
b10010 (
b11111111111111111111111100010010 )
#239
1$
0&
1%
b10001 (
b11111111111111111111111100010001 )
#240
0$
0%
b10000 (
b11111111111111111111111100010000 )
#241
1!
1'
1&
1%
b1111 (
b11111111111111111111111100001111 )
#242
0!
0%
b1110 (
b11111111111111111111111100001110 )
#243
1"
0&
1%
b1101 (
b11111111111111111111111100001101 )
#244
0"
0%
b1100 (
b11111111111111111111111100001100 )
#245
1#
0'
1&
1%
b1011 (
b11111111111111111111111100001011 )
#246
0#
0%
b1010 (
b11111111111111111111111100001010 )
#247
1$
0&
1%
b1001 (
b11111111111111111111111100001001 )
#248
0$
0%
b1000 (
b11111111111111111111111100001000 )
#249
1!
1'
1&
1%
b111 (
b11111111111111111111111100000111 )
#250
0!
0%
b110 (
b11111111111111111111111100000110 )
#251
1"
0&
1%
b101 (
b11111111111111111111111100000101 )
#252
0"
0%
b100 (
b11111111111111111111111100000100 )
#253
1#
0'
1&
1%
b11 (
b11111111111111111111111100000011 )
#254
0#
0%
b10 (
b11111111111111111111111100000010 )
#255
1$
0&
1%
b1 (
b11111111111111111111111100000001 )
#256
0$
0%
b0 (
b11111111111111111111111100000000 )
#257
1!
1'
1&
1%
b111111 (
b11111111111111111111111011111111 )
#258
0!
0%
b111110 (
b11111111111111111111111011111110 )
#259
1"
0&
1%
b111101 (
b11111111111111111111111011111101 )
#260
0"
0%
b111100 (
b11111111111111111111111011111100 )
#261
1#
0'
1&
1%
b111011 (
b11111111111111111111111011111011 )
#262
0#
0%
b111010 (
b11111111111111111111111011111010 )
#263
1$
0&
1%
b111001 (
b11111111111111111111111011111001 )
#264
0$
0%
b111000 (
b11111111111111111111111011111000 )
#265
1!
1'
1&
1%
b110111 (
b11111111111111111111111011110111 )
#266
0!
0%
b110110 (
b11111111111111111111111011110110 )
#267
1"
0&
1%
b110101 (
b11111111111111111111111011110101 )
#268
0"
0%
b110100 (
b11111111111111111111111011110100 )
#269
1#
0'
1&
1%
b110011 (
b11111111111111111111111011110011 )
#270
0#
0%
b110010 (
b11111111111111111111111011110010 )
#271
1$
0&
1%
b110001 (
b11111111111111111111111011110001 )
#272
0$
0%
b110000 (
b11111111111111111111111011110000 )
#273
1!
1'
1&
1%
b101111 (
b11111111111111111111111011101111 )
#274
0!
0%
b101110 (
b11111111111111111111111011101110 )
#275
1"
0&
1%
b101101 (
b11111111111111111111111011101101 )
#276
0"
0%
b101100 (
b11111111111111111111111011101100 )
#277
1#
0'
1&
1%
b101011 (
b11111111111111111111111011101011 )
#278
0#
0%
b101010 (
b11111111111111111111111011101010 )
#279
1$
0&
1%
b101001 (
b11111111111111111111111011101001 )
#280
0$
0%
b101000 (
b11111111111111111111111011101000 )
#281
1!
1'
1&
1%
b100111 (
b11111111111111111111111011100111 )
#282
0!
0%
b100110 (
b11111111111111111111111011100110 )
#283
1"
0&
1%
b100101 (
b11111111111111111111111011100101 )
#284
0"
0%
b100100 (
b11111111111111111111111011100100 )
#285
1#
0'
1&
1%
b100011 (
b11111111111111111111111011100011 )
#286
0#
0%
b100010 (
b11111111111111111111111011100010 )
#287
1$
0&
1%
b100001 (
b11111111111111111111111011100001 )
#288
0$
0%
b100000 (
b11111111111111111111111011100000 )
#289
1!
1'
1&
1%
b11111 (
b11111111111111111111111011011111 )
#290
0!
0%
b11110 (
b11111111111111111111111011011110 )
#291
1"
0&
1%
b11101 (
b11111111111111111111111011011101 )
#292
0"
0%
b11100 (
b11111111111111111111111011011100 )
#293
1#
0'
1&
1%
b11011 (
b11111111111111111111111011011011 )
#294
0#
0%
b11010 (
b11111111111111111111111011011010 )
#295
1$
0&
1%
b11001 (
b11111111111111111111111011011001 )
#296
0$
0%
b11000 (
b11111111111111111111111011011000 )
#297
1!
1'
1&
1%
b10111 (
b11111111111111111111111011010111 )
#298
0!
0%
b10110 (
b11111111111111111111111011010110 )
#299
1"
0&
1%
b10101 (
b11111111111111111111111011010101 )
#300
0"
0%
b10100 (
b11111111111111111111111011010100 )
#301
1#
0'
1&
1%
b10011 (
b11111111111111111111111011010011 )
#302
0#
0%
b10010 (
b11111111111111111111111011010010 )
#303
1$
0&
1%
b10001 (
b11111111111111111111111011010001 )
#304
0$
0%
b10000 (
b11111111111111111111111011010000 )
#305
1!
1'
1&
1%
b1111 (
b11111111111111111111111011001111 )
#306
0!
0%
b1110 (
b11111111111111111111111011001110 )
#307
1"
0&
1%
b1101 (
b11111111111111111111111011001101 )
#308
0"
0%
b1100 (
b11111111111111111111111011001100 )
#309
1#
0'
1&
1%
b1011 (
b11111111111111111111111011001011 )
#310
0#
0%
b1010 (
b11111111111111111111111011001010 )
#311
1$
0&
1%
b1001 (
b11111111111111111111111011001001 )
#312
0$
0%
b1000 (
b11111111111111111111111011001000 )
#313
1!
1'
1&
1%
b111 (
b11111111111111111111111011000111 )
#314
0!
0%
b110 (
b11111111111111111111111011000110 )
#315
1"
0&
1%
b101 (
b11111111111111111111111011000101 )
#316
0"
0%
b100 (
b11111111111111111111111011000100 )
#317
1#
0'
1&
1%
b11 (
b11111111111111111111111011000011 )
#318
0#
0%
b10 (
b11111111111111111111111011000010 )
#319
1$
0&
1%
b1 (
b11111111111111111111111011000001 )
#320
0$
0%
b0 (
b11111111111111111111111011000000 )
#321
1!
1'
1&
1%
b111111 (
b11111111111111111111111010111111 )
#322
0!
0%
b111110 (
b11111111111111111111111010111110 )
#323
1"
0&
1%
b111101 (
b11111111111111111111111010111101 )
#324
0"
0%
b111100 (
b11111111111111111111111010111100 )
#325
1#
0'
1&
1%
b111011 (
b11111111111111111111111010111011 )
#326
0#
0%
b111010 (
b11111111111111111111111010111010 )
#327
1$
0&
1%
b111001 (
b11111111111111111111111010111001 )
#328
0$
0%
b111000 (
b11111111111111111111111010111000 )
#329
1!
1'
1&
1%
b110111 (
b11111111111111111111111010110111 )
#330
0!
0%
b110110 (
b11111111111111111111111010110110 )
#331
1"
0&
1%
b110101 (
b11111111111111111111111010110101 )
#332
0"
0%
b110100 (
b11111111111111111111111010110100 )
#333
1#
0'
1&
1%
b110011 (
b11111111111111111111111010110011 )
#334
0#
0%
b110010 (
b11111111111111111111111010110010 )
#335
1$
0&
1%
b110001 (
b11111111111111111111111010110001 )
#336
0$
0%
b110000 (
b11111111111111111111111010110000 )
#337
1!
1'
1&
1%
b101111 (
b11111111111111111111111010101111 )
#338
0!
0%
b101110 (
b11111111111111111111111010101110 )
#339
1"
0&
1%
b101101 (
b11111111111111111111111010101101 )
#340
0"
0%
b101100 (
b11111111111111111111111010101100 )
#341
1#
0'
1&
1%
b101011 (
b11111111111111111111111010101011 )
#342
0#
0%
b101010 (
b11111111111111111111111010101010 )
#343
1$
0&
1%
b101001 (
b11111111111111111111111010101001 )
#344
0$
0%
b101000 (
b11111111111111111111111010101000 )
#345
1!
1'
1&
1%
b100111 (
b11111111111111111111111010100111 )
#346
0!
0%
b100110 (
b11111111111111111111111010100110 )
#347
1"
0&
1%
b100101 (
b11111111111111111111111010100101 )
#348
0"
0%
b100100 (
b11111111111111111111111010100100 )
#349
1#
0'
1&
1%
b100011 (
b11111111111111111111111010100011 )
#350
0#
0%
b100010 (
b11111111111111111111111010100010 )
#351
1$
0&
1%
b100001 (
b11111111111111111111111010100001 )
#352
0$
0%
b100000 (
b11111111111111111111111010100000 )
#353
1!
1'
1&
1%
b11111 (
b11111111111111111111111010011111 )
#354
0!
0%
b11110 (
b11111111111111111111111010011110 )
#355
1"
0&
1%
b11101 (
b11111111111111111111111010011101 )
#356
0"
0%
b11100 (
b11111111111111111111111010011100 )
#357
1#
0'
1&
1%
b11011 (
b11111111111111111111111010011011 )
#358
0#
0%
b11010 (
b11111111111111111111111010011010 )
#359
1$
0&
1%
b11001 (
b11111111111111111111111010011001 )
#360
0$
0%
b11000 (
b11111111111111111111111010011000 )
#361
1!
1'
1&
1%
b10111 (
b11111111111111111111111010010111 )
#362
0!
0%
b10110 (
b11111111111111111111111010010110 )
#363
1"
0&
1%
b10101 (
b11111111111111111111111010010101 )
#364
0"
0%
b10100 (
b11111111111111111111111010010100 )
#365
1#
0'
1&
1%
b10011 (
b11111111111111111111111010010011 )
#366
0#
0%
b10010 (
b11111111111111111111111010010010 )
#367
1$
0&
1%
b10001 (
b11111111111111111111111010010001 )
#368
0$
0%
b10000 (
b11111111111111111111111010010000 )
#369
1!
1'
1&
1%
b1111 (
b11111111111111111111111010001111 )
#370
0!
0%
b1110 (
b11111111111111111111111010001110 )
#371
1"
0&
1%
b1101 (
b11111111111111111111111010001101 )
#372
0"
0%
b1100 (
b11111111111111111111111010001100 )
#373
1#
0'
1&
1%
b1011 (
b11111111111111111111111010001011 )
#374
0#
0%
b1010 (
b11111111111111111111111010001010 )
#375
1$
0&
1%
b1001 (
b11111111111111111111111010001001 )
#376
0$
0%
b1000 (
b11111111111111111111111010001000 )
#377
1!
1'
1&
1%
b111 (
b11111111111111111111111010000111 )
#378
0!
0%
b110 (
b11111111111111111111111010000110 )
#379
1"
0&
1%
b101 (
b11111111111111111111111010000101 )
#380
0"
0%
b100 (
b11111111111111111111111010000100 )
#381
1#
0'
1&
1%
b11 (
b11111111111111111111111010000011 )
#382
0#
0%
b10 (
b11111111111111111111111010000010 )
#383
1$
0&
1%
b1 (
b11111111111111111111111010000001 )
#384
0$
0%
b0 (
b11111111111111111111111010000000 )
#385
1!
1'
1&
1%
b111111 (
b11111111111111111111111001111111 )
#386
0!
0%
b111110 (
b11111111111111111111111001111110 )
#387
1"
0&
1%
b111101 (
b11111111111111111111111001111101 )
#388
0"
0%
b111100 (
b11111111111111111111111001111100 )
#389
1#
0'
1&
1%
b111011 (
b11111111111111111111111001111011 )
#390
0#
0%
b111010 (
b11111111111111111111111001111010 )
#391
1$
0&
1%
b111001 (
b11111111111111111111111001111001 )
#392
0$
0%
b111000 (
b11111111111111111111111001111000 )
#393
1!
1'
1&
1%
b110111 (
b11111111111111111111111001110111 )
#394
0!
0%
b110110 (
b11111111111111111111111001110110 )
#395
1"
0&
1%
b110101 (
b11111111111111111111111001110101 )
#396
0"
0%
b110100 (
b11111111111111111111111001110100 )
#397
1#
0'
1&
1%
b110011 (
b11111111111111111111111001110011 )
#398
0#
0%
b110010 (
b11111111111111111111111001110010 )
#399
1$
0&
1%
b110001 (
b11111111111111111111111001110001 )
#400
0$
0%
b110000 (
b11111111111111111111111001110000 )
#401
1!
1'
1&
1%
b101111 (
b11111111111111111111111001101111 )
#402
0!
0%
b101110 (
b11111111111111111111111001101110 )
#403
1"
0&
1%
b101101 (
b11111111111111111111111001101101 )
#404
0"
0%
b101100 (
b11111111111111111111111001101100 )
#405
1#
0'
1&
1%
b101011 (
b11111111111111111111111001101011 )
#406
0#
0%
b101010 (
b11111111111111111111111001101010 )
#407
1$
0&
1%
b101001 (
b11111111111111111111111001101001 )
#408
0$
0%
b101000 (
b11111111111111111111111001101000 )
#409
1!
1'
1&
1%
b100111 (
b11111111111111111111111001100111 )
#410
0!
0%
b100110 (
b11111111111111111111111001100110 )
#411
1"
0&
1%
b100101 (
b11111111111111111111111001100101 )
#412
0"
0%
b100100 (
b11111111111111111111111001100100 )
#413
1#
0'
1&
1%
b100011 (
b11111111111111111111111001100011 )
#414
0#
0%
b100010 (
b11111111111111111111111001100010 )
#415
1$
0&
1%
b100001 (
b11111111111111111111111001100001 )
#416
0$
0%
b100000 (
b11111111111111111111111001100000 )
#417
1!
1'
1&
1%
b11111 (
b11111111111111111111111001011111 )
#418
0!
0%
b11110 (
b11111111111111111111111001011110 )
#419
1"
0&
1%
b11101 (
b11111111111111111111111001011101 )
#420
0"
0%
b11100 (
b11111111111111111111111001011100 )
#421
1#
0'
1&
1%
b11011 (
b11111111111111111111111001011011 )
#422
0#
0%
b11010 (
b11111111111111111111111001011010 )
#423
1$
0&
1%
b11001 (
b11111111111111111111111001011001 )
#424
0$
0%
b11000 (
b11111111111111111111111001011000 )
#425
1!
1'
1&
1%
b10111 (
b11111111111111111111111001010111 )
#426
0!
0%
b10110 (
b11111111111111111111111001010110 )
#427
1"
0&
1%
b10101 (
b11111111111111111111111001010101 )
#428
0"
0%
b10100 (
b11111111111111111111111001010100 )
#429
1#
0'
1&
1%
b10011 (
b11111111111111111111111001010011 )
#430
0#
0%
b10010 (
b11111111111111111111111001010010 )
#431
1$
0&
1%
b10001 (
b11111111111111111111111001010001 )
#432
0$
0%
b10000 (
b11111111111111111111111001010000 )
#433
1!
1'
1&
1%
b1111 (
b11111111111111111111111001001111 )
#434
0!
0%
b1110 (
b11111111111111111111111001001110 )
#435
1"
0&
1%
b1101 (
b11111111111111111111111001001101 )
#436
0"
0%
b1100 (
b11111111111111111111111001001100 )
#437
1#
0'
1&
1%
b1011 (
b11111111111111111111111001001011 )
